<f a="0xe240" c="1" t="10552.144476" lt="0.104483" ch="3" cht="10552.039994">
 <f a="0x1929" c="1" t="1.129473" lt="0.089676" ch="6" cht="1.039797">
  <f n="maCheckInterfaceVersion" c="1" t="0.964089" lt="0.964089" ch="0" cht="0.000000">
  </f>
  <f a="0xa064" c="1" t="0.060902" lt="0.026819" ch="2" cht="0.034083">
   <f n="memset" c="1" t="0.017600" lt="0.017600" ch="0" cht="0.000000">
   </f>
   <f a="0x9b81" c="1" t="0.016483" lt="0.016483" ch="0" cht="0.000000">
   </f>
  </f>
  <f a="0x18cd" c="1" t="0.004190" lt="0.004190" ch="0" cht="0.000000">
  </f>
  <f a="0x18fb" c="1" t="0.003632" lt="0.003632" ch="0" cht="0.000000">
  </f>
  <f a="0x18e4" c="1" t="0.003632" lt="0.003632" ch="0" cht="0.000000">
  </f>
  <f a="0x1912" c="1" t="0.003352" lt="0.003352" ch="0" cht="0.000000">
  </f>
 </f>
 <f a="0x139c" c="1" t="0.096660" lt="0.009778" ch="1" cht="0.086883">
  <f a="0x1fbc2" c="1" t="0.086883" lt="0.028495" ch="1" cht="0.058387">
   <f a="0x1fb5e" c="1" t="0.058387" lt="0.010057" ch="1" cht="0.048330">
    <f a="0x2d8" c="1" t="0.048330" lt="0.011733" ch="1" cht="0.036597">
     <f a="0x2e8" c="1" t="0.036597" lt="0.006984" ch="1" cht="0.029613">
      <f a="0x19cf" c="1" t="0.029613" lt="0.007822" ch="1" cht="0.021790">
       <f a="0xa8ef" c="1" t="0.021790" lt="0.009498" ch="1" cht="0.012292">
        <f a="0xa38e" c="1" t="0.012292" lt="0.012292" ch="0" cht="0.000000">
        </f>
       </f>
      </f>
     </f>
    </f>
   </f>
  </f>
 </f>
 <f a="0x164" c="1" t="10550.813860" lt="0.031289" ch="6" cht="10550.782572">
  <f a="0x2e8" c="1" t="0.029892" lt="0.007263" ch="1" cht="0.022629">
   <f a="0x19cf" c="1" t="0.022629" lt="0.007263" ch="1" cht="0.015365">
    <f a="0xa8ef" c="1" t="0.015365" lt="0.007263" ch="1" cht="0.008102">
     <f a="0xa38e" c="1" t="0.008102" lt="0.008102" ch="0" cht="0.000000">
     </f>
    </f>
   </f>
  </f>
  <f a="0x1ed31" c="1" t="0.698133" lt="0.241651" ch="5" cht="0.456483">
   <f a="0x1825e" c="1" t="0.422679" lt="0.052521" ch="1" cht="0.370159">
    <f a="0x2d8" c="10" t="0.370159" lt="0.068165" ch="1" cht="0.301994">
     <f a="0x2e8" c="10" t="0.301994" lt="0.085206" ch="1" cht="0.216787">
      <f a="0x19cf" c="10" t="0.216787" lt="0.074032" ch="1" cht="0.142756">
       <f a="0xa8ef" c="10" t="0.142756" lt="0.069841" ch="1" cht="0.072914">
        <f a="0xa38e" c="10" t="0.072914" lt="0.072914" ch="0" cht="0.000000">
        </f>
       </f>
      </f>
     </f>
    </f>
   </f>
   <f a="0x19d70" c="1" t="0.009219" lt="0.009219" ch="0" cht="0.000000">
   </f>
   <f a="0x1b3e0" c="1" t="0.010616" lt="0.010616" ch="0" cht="0.000000">
   </f>
   <f a="0x185bf" c="1" t="0.004749" lt="0.004749" ch="0" cht="0.000000">
   </f>
   <f a="0x1d05f" c="1" t="0.009219" lt="0.009219" ch="0" cht="0.000000">
   </f>
  </f>
  <f n="maSetColor" c="1" t="0.142197" lt="0.142197" ch="0" cht="0.000000">
  </f>
  <f n="maDrawText" c="1" t="1.503543" lt="1.503543" ch="0" cht="0.000000">
  </f>
  <f n="maUpdateScreen" c="1" t="5.120204" lt="5.120204" ch="0" cht="0.000000">
  </f>
  <f a="0x1f50a" c="1" t="10543.288602" lt="1.376991" ch="11" cht="10541.911612">
   <f n="maGetEvent" c="50" t="0.551467" lt="0.551467" ch="0" cht="0.000000">
   </f>
   <f a="0x1efca" c="25" t="0.667403" lt="0.416813" ch="2" cht="0.250591">
    <f n="maGetMilliSecondCount" c="25" t="0.136610" lt="0.136610" ch="0" cht="0.000000">
    </f>
    <f n="memcpy" c="25" t="0.113981" lt="0.113981" ch="0" cht="0.000000">
    </f>
   </f>
   <f a="0x1bd9f" c="25" t="0.435530" lt="0.321270" ch="1" cht="0.114260">
    <f n="memcpy" c="25" t="0.114260" lt="0.114260" ch="0" cht="0.000000">
    </f>
   </f>
   <f a="0x1ee7f" c="25" t="0.718527" lt="0.483302" ch="2" cht="0.235225">
    <f n="maGetMilliSecondCount" c="25" t="0.120127" lt="0.120127" ch="0" cht="0.000000">
    </f>
    <f n="memcpy" c="25" t="0.115098" lt="0.115098" ch="0" cht="0.000000">
    </f>
   </f>
   <f n="maWait" c="25" t="10315.235037" lt="10315.235037" ch="0" cht="0.000000">
   </f>
   <f a="0x1ae1d" c="1" t="0.037156" lt="0.021790" ch="2" cht="0.015365">
    <f n="memcpy" c="1" t="0.004190" lt="0.004190" ch="0" cht="0.000000">
    </f>
    <f a="0x1b" c="1" t="0.011175" lt="0.007543" ch="1" cht="0.003632">
     <f a="0x2f" c="1" t="0.003632" lt="0.003632" ch="0" cht="0.000000">
     </f>
    </f>
   </f>
   <f a="0x1a54d" c="1" t="0.029892" lt="0.015924" ch="2" cht="0.013968">
    <f n="memcpy" c="1" t="0.003352" lt="0.003352" ch="0" cht="0.000000">
    </f>
    <f a="0x7e" c="1" t="0.010616" lt="0.007263" ch="1" cht="0.003352">
     <f a="0x92" c="1" t="0.003352" lt="0.003352" ch="0" cht="0.000000">
     </f>
    </f>
   </f>
   <f a="0x1a841" c="1" t="0.035479" lt="0.016762" ch="2" cht="0.018717">
    <f n="memcpy" c="1" t="0.007543" lt="0.007543" ch="0" cht="0.000000">
    </f>
    <f a="0x5d" c="1" t="0.011175" lt="0.007822" ch="1" cht="0.003352">
     <f a="0x71" c="1" t="0.003352" lt="0.003352" ch="0" cht="0.000000">
     </f>
    </f>
   </f>
   <f a="0x19f65" c="1" t="0.027937" lt="0.013130" ch="2" cht="0.014806">
    <f n="memcpy" c="1" t="0.003632" lt="0.003632" ch="0" cht="0.000000">
    </f>
    <f a="0xc0" c="1" t="0.011175" lt="0.007822" ch="1" cht="0.003352">
     <f a="0xd4" c="1" t="0.003352" lt="0.003352" ch="0" cht="0.000000">
     </f>
    </f>
   </f>
   <f a="0x197a0" c="12" t="223.609425" lt="0.318197" ch="3" cht="223.291228">
    <f n="memcpy" c="12" t="0.068165" lt="0.068165" ch="0" cht="0.000000">
    </f>
    <f a="0x1" c="12" t="0.058667" lt="0.058667" ch="0" cht="0.000000">
    </f>
    <f a="0x102" c="12" t="223.164397" lt="0.123200" ch="1" cht="223.041197">
     <f a="0x116" c="12" t="223.041197" lt="0.065651" ch="1" cht="222.975546">
      <f a="0x1ee51" c="1" t="222.975546" lt="0.008940" ch="1" cht="222.966606">
       <f n="maExit" c="1" t="222.966606" lt="222.966606" ch="0" cht="0.000000">
       </f>
      </f>
     </f>
    </f>
   </f>
   <f a="0x194a3" c="11" t="0.563759" lt="0.252546" ch="3" cht="0.311213">
    <f n="memcpy" c="11" t="0.062578" lt="0.062578" ch="0" cht="0.000000">
    </f>
    <f a="0xe" c="11" t="0.054756" lt="0.054756" ch="0" cht="0.000000">
    </f>
    <f a="0x143" c="11" t="0.193879" lt="0.142756" ch="1" cht="0.051124">
     <f a="0x157" c="11" t="0.051124" lt="0.051124" ch="0" cht="0.000000">
     </f>
    </f>
   </f>
  </f>
 </f>
</f>
